typed_args/__init__.py
typed_args/_assigner.py
typed_args/_core.py
typed_args/_parser.py
typed_args/_utils.py
typed_args-0.6.5.dist-info/METADATA
typed_args-0.6.5.dist-info/WHEEL
typed_args-0.6.5.dist-info/licenses/LICENSE
typed_args-0.6.5.dist-info/RECORD
