Metadata-Version: 2.3
Name: typed-args
Version: 0.6.5
Summary: Parse command line arguments by defining dataclasses
Project-URL: Homepage, https://github.com/SunDoge/typed-args
Project-URL: Repository, https://github.com/SunDoge/typed-args
Author-email: SunDoge <triplez0@outlook.com>
License: BSD 3-Clause License
License-File: LICENSE
Keywords: argparse,cli
Classifier: License :: OSI Approved :: MIT License
Classifier: Operating System :: OS Independent
Classifier: Programming Language :: Python :: 3
Requires-Python: >=3.6
